Metadata-Version: 1.1
Name: feedj
Version: 0.0.1
Summary: feeding j
Home-page: https://github.com/mlcristina/feedj
Author: mcc
Author-email: cristina.caputo+test@gmail.com
License: none
Download-URL: https://github.com/mlcristina/feedj/archive/0.0.1.tar.gz
Keywords: python
Platform: UNKNOWN
Classifier: Topic :: Software Development :: Libraries
Classifier: Programming Language :: Python
Classifier: Intended Audience :: Developers
Classifier: Programming Language :: Python :: 2.6
Classifier: Programming Language :: Python :: 2.7
Classifier: Programming Language :: Python :: 3.3
Classifier: Programming Language :: Python :: 3.4
Classifier: Programming Language :: Python :: 3.5
Classifier: Programming Language :: Python :: 3.6
Classifier: Programming Language :: Python :: 3.7
Classifier: Programming Language :: Python :: 3.8
